{
    "BatchSize": "",
    "Description": "",
    "ExpectedInputJson": "",
    "ExpectedInputOtherData": "",
    "ExpectedInputXml": "",
    "ExpectedOutputJson": "",
    "ExpectedOutputOtherData": "",
    "ExpectedOutputXml": "",
    "GlobalKey": "DREAtGlanceOnboardingCase",
    "InputParsingClass": "",
    "InputType": "JSON",
    "IsAssignmentRulesUsed": false,
    "IsDeletedOnSuccess": false,
    "IsErrorIgnored": false,
    "IsFieldLevelSecurityEnabled": true,
    "IsManagedUsingStdDesigner": false,
    "IsNullInputsIncludedInOutput": true,
    "IsProcessSuperBulk": false,
    "IsRollbackOnError": false,
    "IsSourceObjectDefault": false,
    "IsXmlDeclarationRemoved": false,
    "Name": "DREAtGlanceOnboardingCase",
    "Namespace": "",
    "OmniDataTransformItem": "DREAtGlanceOnboardingCase_Items.json",
    "OutputParsingClass": "",
    "OutputType": "JSON",
    "OverrideKey": "",
    "PreprocessorClassName": "",
    "PreviewJsonData": "DREAtGlanceOnboardingCase_SampleInputJson.json",
    "PreviewOtherData": "",
    "PreviewSourceObjectData": "",
    "PreviewXmlData": "",
    "RequiredPermission": "",
    "ResponseCacheTtlMinutes": 0,
    "ResponseCacheType": "",
    "SourceObject": "json",
    "SynchronousProcessThreshold": 0,
    "TargetOutputDocumentIdentifier": "",
    "TargetOutputFileName": "",
    "Type": "Extract",
    "UniqueName": "DREAtGlanceOnboardingCase_1",
    "VersionNumber": 1,
    "VlocityDataPackType": "SObject",
    "VlocityRecordSObjectType": "OmniDataTransform",
    "VlocityRecordSourceKey": "OmniDataTransform/DREAtGlanceOnboardingCase",
    "XmlOutputTagsOrder": ""
}